ipyannote/__init__.py
ipyannote/apps/__init__.py
ipyannote/apps/annotation.py
ipyannote/apps/der.py
ipyannote/apps/transcription.py
ipyannote/apps/wer.py
ipyannote/blocks/__init__.py
ipyannote/blocks/controls.py
ipyannote/blocks/htranscript.py
ipyannote/blocks/labels.py
ipyannote/blocks/vtranscript.py
ipyannote/blocks/waveform.py
ipyannote/static/controls.css
ipyannote/static/controls.js
ipyannote/static/htranscript.css
ipyannote/static/htranscript.js
ipyannote/static/labels.css
ipyannote/static/labels.js
ipyannote/static/vtranscript.css
ipyannote/static/vtranscript.js
ipyannote/static/waveform.css
ipyannote/static/waveform.js
ipyannote/utils/__init__.py
ipyannote/utils/load.py
ipyannote/utils/sync.py
ipyannote-0.3.0.dist-info/METADATA
ipyannote-0.3.0.dist-info/WHEEL
ipyannote-0.3.0.dist-info/RECORD
