Metadata-Version: 2.4
Name: ipyannote
Version: 0.3.0
Summary: Interactive pyannote widgets
Author-email: Hervé BREDIN <herve@pyannote.ai>
Requires-Python: >=3.10
Requires-Dist: anywidget>=0.9.13
Requires-Dist: numpy>=1.0.0
Requires-Dist: pyannote-core>=5.0.0
Requires-Dist: pyannote-metrics>=3.2.1
Requires-Dist: scipy>=1.14.1
Provides-Extra: wer
Requires-Dist: meeteval>=0.4.3; extra == 'wer'
